[
    {"name": "GBP", "GBP": 1, "EUR": 1.3871, "CHF": 1.3868, "USD": 1.3865, "JPY": 1, "CAD": 1.23, "NZD": 1.6533, "AUD": 5.3453, "ZAR": 4.3452, "RUB": 34.3432},
    {"name": "EUR", "GBP": 1, "EUR": 1.3871, "CHF": 1.3868, "USD": 1.3865, "JPY": 1, "CAD": 1.23, "NZD": 1.6533, "AUD": 5.3453, "ZAR": 4.3452, "RUB": 34.3432},
    {"name": "CHF", "GBP": 1, "EUR": 1.3871, "CHF": 1.3868, "USD": 1.3865, "JPY": 1, "CAD": 1.23, "NZD": 1.6533, "AUD": 5.3453, "ZAR": 4.3452, "RUB": 34.3432},
    {"name": "USD", "GBP": 1, "EUR": 1.3871, "CHF": 1.3868, "USD": 1.3865, "JPY": 1, "CAD": 1.23, "NZD": 1.6533, "AUD": 5.3453, "ZAR": 4.3452, "RUB": 34.3432},    
    {"name": "JPY", "GBP": 1, "EUR": 1.3871, "CHF": 1.3868, "USD": 1.3865, "JPY": 1, "CAD": 1.23, "NZD": 1.6533, "AUD": 5.3453, "ZAR": 4.3452, "RUB": 34.3432},    
    {"name": "CAD", "GBP": 1, "EUR": 1.3871, "CHF": 1.3868, "USD": 1.3865, "JPY": 1, "CAD": 1.23, "NZD": 1.6533, "AUD": 5.3453, "ZAR": 4.3452, "RUB": 34.3432},    
    {"name": "NZD", "GBP": 1, "EUR": 1.3871, "CHF": 1.3868, "USD": 1.3865, "JPY": 1, "CAD": 1.23, "NZD": 1.6533, "AUD": 5.3453, "ZAR": 4.3452, "RUB": 34.3432},    
    {"name": "AUD", "GBP": 1, "EUR": 1.3871, "CHF": 1.3868, "USD": 1.3865, "JPY": 1, "CAD": 1.23, "NZD": 1.6533, "AUD": 5.3453, "ZAR": 4.3452, "RUB": 34.3432},
    {"name": "ZAR", "GBP": 1, "EUR": 1.3871, "CHF": 1.3868, "USD": 1.3865, "JPY": 1, "CAD": 1.23, "NZD": 1.6533, "AUD": 5.3453, "ZAR": 4.3452, "RUB": 34.3432},    
    {"name": "RUB", "GBP": 1, "EUR": 1.3871, "CHF": 1.3868, "USD": 1.3865, "JPY": 1, "CAD": 1.23, "NZD": 1.6533, "AUD": 5.3453, "ZAR": 4.3452, "RUB": 34.3432}
];